{
  "version": "3.3.1",
  "flags": {},
  "shapes": [
    {
      "label": "Neptune",
      "score": null,
      "points": [
        [
          153.0,
          21.0
        ],
        [
          487.0,
          21.0
        ],
        [
          487.0,
          616.0
        ],
        [
          153.0,
          616.0
        ]
      ],
      "group_id": null,
      "description": null,
      "difficult": false,
      "shape_type": "rectangle",
      "flags": {},
      "attributes": {},
      "kie_linking": []
    }
  ],
  "imagePath": "Neptune (583).jpg",
  "imageData": null,
  "imageHeight": 640,
  "imageWidth": 640
}