{
  "version": "3.3.1",
  "flags": {},
  "shapes": [
    {
      "label": "Venus",
      "score": null,
      "points": [
        [
          96.0,
          0.0
        ],
        [
          497.0,
          0.0
        ],
        [
          497.0,
          635.0
        ],
        [
          96.0,
          635.0
        ]
      ],
      "group_id": null,
      "description": null,
      "difficult": false,
      "shape_type": "rectangle",
      "flags": {},
      "attributes": {},
      "kie_linking": []
    }
  ],
  "imagePath": "Venus (491).jpg",
  "imageData": null,
  "imageHeight": 640,
  "imageWidth": 640
}